whitebox_plugin_traffic_display/__init__.py
whitebox_plugin_traffic_display/apps.py
whitebox_plugin_traffic_display/jsx/TrafficDisplayServiceComponent.jsx
whitebox_plugin_traffic_display/jsx/TrafficMarkers.jsx
whitebox_plugin_traffic_display/jsx/UnknownTraffic.jsx
whitebox_plugin_traffic_display/jsx/map_layers/TrafficFlightPath.jsx
whitebox_plugin_traffic_display/jsx/stores/traffic.js
whitebox_plugin_traffic_display/jsx/stores/traffic.test.js
whitebox_plugin_traffic_display/static/whitebox_plugin_traffic_display/assets/plane.svg
whitebox_plugin_traffic_display/urls.py
whitebox_plugin_traffic_display/utils.py
whitebox_plugin_traffic_display/views.py
whitebox_plugin_traffic_display/whitebox_plugin_traffic_display.py
whitebox_test_plugin_traffic_display/__init__.py
whitebox_test_plugin_traffic_display/federation/traffic_markers.spec.js
whitebox_test_plugin_traffic_display/test_whitebox_plugin_traffic_display.py
whitebox_plugin_traffic_display-0.1.9.dist-info/LICENSE
whitebox_plugin_traffic_display-0.1.9.dist-info/METADATA
whitebox_plugin_traffic_display-0.1.9.dist-info/WHEEL
whitebox_plugin_traffic_display-0.1.9.dist-info/entry_points.txt
whitebox_plugin_traffic_display-0.1.9.dist-info/RECORD
